{
  "project_info": {
    "project_number": "986469609932",
    "project_id": "auto-fx-flutter",
    "storage_bucket": "auto-fx-flutter.appspot.com"
  },
  "client": [
    {
      "client_info": {
        "mobilesdk_app_id": "1:986469609932:android:8432257c1eb272558b2d69",
        "android_client_info": {
          "package_name": "com.example.auto_fx_flutter"
        }
      },
      "oauth_client": [
        {
          "client_id": "986469609932-imv8faiqafb1q115h6b63869fr8boi9f.apps.googleusercontent.com",
          "client_type": 1,
          "android_info": {
            "package_name": "com.example.auto_fx_flutter",
            "certificate_hash": "9cad670ba23b42b7d31f95b35672a544f7d576cb"
          }
        },
        {
          "client_id": "986469609932-i6aclsckb5fgr677r1t9tjall3oce8ji.apps.googleusercontent.com",
          "client_type": 3
        }
      ],
      "api_key": [
        {
          "current_key": "AIzaSyCiKLSWf_K4fL8KgauT3ajnq1miHkb34tQ"
        }
      ],
      "services": {
        "appinvite_service": {
          "other_platform_oauth_client": [
            {
              "client_id": "986469609932-i6aclsckb5fgr677r1t9tjall3oce8ji.apps.googleusercontent.com",
              "client_type": 3
            }
          ]
        }
      }
    }
  ],
  "configuration_version": "1"
}